rt_pie_lib/__init__.py
rt_pie_lib/converters/__init__.py
rt_pie_lib/metrics/__init__.py
rt_pie_lib/metrics/unvoiced_detector/__init__.py
rt_pie_lib-0.1.12.dist-info/WHEEL
rt_pie_lib-0.1.12.dist-info/METADATA
rt_pie_lib-0.1.12.dist-info/RECORD
